odoo/addons/picking_very_high_priority/README.rst
odoo/addons/picking_very_high_priority/__init__.py
odoo/addons/picking_very_high_priority/__manifest__.py
odoo/addons/picking_very_high_priority/i18n/es.po
odoo/addons/picking_very_high_priority/models/__init__.py
odoo/addons/picking_very_high_priority/models/stock_move.py
odoo/addons/picking_very_high_priority/models/stock_picking.py
odoo/addons/picking_very_high_priority/static/description/icon.png
odoo_addon_picking_very_high_priority-15.0.1.0.0.2.dist-info/METADATA
odoo_addon_picking_very_high_priority-15.0.1.0.0.2.dist-info/WHEEL
odoo_addon_picking_very_high_priority-15.0.1.0.0.2.dist-info/top_level.txt
odoo_addon_picking_very_high_priority-15.0.1.0.0.2.dist-info/RECORD
