Metadata-Version: 2.1
Name: odoo-addon-picking_very_high_priority
Version: 15.0.1.0.0.2
Requires-Python: >=3.8
Requires-Dist: odoo>=15.0a,<15.1dev
Summary: Picking Very High Priority
Home-page: https://github.com/sygel-technology/sy-stock-logistics-workflow
License: AGPL-3
Author: Sygel, Odoo Community Association (OCA)
Author-email: support@odoo-community.org
Classifier: Programming Language :: Python
Classifier: Framework :: Odoo
Classifier: Framework :: Odoo :: 15.0
Classifier: License :: OSI Approved :: GNU Affero General Public License v3
